{
  "tracjectory": [
    {
      "frameInt": 1,
      "beforeTrans_pos": [
        1323,
        466
      ],
      "beforeTrans_chestDirection": [
        1304,
        398
      ],
      "pos": [
        1440,
        630
      ],
      "direction": [
        1421,
        534
      ],
      "state": "walkableArea"
    },
    {
      "frameInt": 2,
      "beforeTrans_pos": [
        1323,
        466
      ],
      "beforeTrans_chestDirection": [
        1304,
        398
      ],
      "pos": [
        1440,
        630
      ],
      "direction": [
        1421,
        534
      ],
      "state": "walkableArea"
    },
    {
      "frameInt": 3,
      "beforeTrans_pos": [
        1323,
        466
      ],
      "beforeTrans_chestDirection": [
        1304,
        398
      ],
      "pos": [
        1440,
        630
      ],
      "direction": [
        1421,
        534
      ],
      "state": "walkableArea"
    },
    {
      "frameInt": 4,
      "beforeTrans_pos": [
        1323,
        466
      ],
      "beforeTrans_chestDirection": [
        1393,
        466
      ],
      "pos": [
        1440,
        630
      ],
      "direction": [
        1507,
        630
      ],
      "state": "walkableArea"
    },
    {
      "frameInt": 5,
      "beforeTrans_pos": [
        1318,
        459
      ],
      "beforeTrans_chestDirection": [
        1299,
        391
      ],
      "pos": [
        1436,
        621
      ],
      "direction": [
        1415,
        523
      ],
      "state": "walkableArea"
    },
    {
      "frameInt": 6,
      "beforeTrans_pos": [
        1318,
        459
      ],
      "beforeTrans_chestDirection": [
        1299,
        391
      ],
      "pos": [
        1436,
        621
      ],
      "direction": [
        1415,
        523
      ],
      "state": "walkableArea"
    },
    {
      "frameInt": 7,
      "beforeTrans_pos": [
        1321,
        462
      ],
      "beforeTrans_chestDirection": [
        1302,
        394
      ],
      "pos": [
        1439,
        625
      ],
      "direction": [
        1419,
        528
      ],
      "state": "walkableArea"
    },
    {
      "frameInt": 8,
      "beforeTrans_pos": [
        1318,
        471
      ],
      "beforeTrans_chestDirection": [
        1318,
        401
      ],
      "pos": [
        1436,
        636
      ],
      "direction": [
        1436,
        539
      ],
      "state": "walkableArea"
    },
    {
      "frameInt": 9,
      "beforeTrans_pos": [
        1306,
        466
      ],
      "beforeTrans_chestDirection": [
        1306,
        396
      ],
      "pos": [
        1424,
        630
      ],
      "direction": [
        1423,
        531
      ],
      "state": "walkableArea"
    },
    {
      "frameInt": 10,
      "beforeTrans_pos": [
        1299,
        465
      ],
      "beforeTrans_chestDirection": [
        1299,
        395
      ],
      "pos": [
        1417,
        629
      ],
      "direction": [
        1416,
        530
      ],
      "state": "walkableArea"
    },
    {
      "frameInt": 11,
      "beforeTrans_pos": [
        1301,
        467
      ],
      "beforeTrans_chestDirection": [
        1301,
        397
      ],
      "pos": [
        1419,
        631
      ],
      "direction": [
        1418,
        533
      ],
      "state": "walkableArea"
    },
    {
      "frameInt": 12,
      "beforeTrans_pos": [
        1299,
        468
      ],
      "beforeTrans_chestDirection": [
        1299,
        398
      ],
      "pos": [
        1418,
        633
      ],
      "direction": [
        1416,
        534
      ],
      "state": "walkableArea"
    },
    {
      "frameInt": 13,
      "beforeTrans_pos": [
        1302,
        464
      ],
      "beforeTrans_chestDirection": [
        1302,
        394
      ],
      "pos": [
        1420,
        628
      ],
      "direction": [
        1419,
        528
      ],
      "state": "walkableArea"
    },
    {
      "frameInt": 14,
      "beforeTrans_pos": [
        1306,
        459
      ],
      "beforeTrans_chestDirection": [
        1355,
        409
      ],
      "pos": [
        1424,
        621
      ],
      "direction": [
        1475,
        552
      ],
      "state": "walkableArea"
    },
    {
      "frameInt": 15,
      "beforeTrans_pos": [
        1362,
        436
      ],
      "beforeTrans_chestDirection": [
        1411,
        386
      ],
      "pos": [
        1480,
        591
      ],
      "direction": [
        1537,
        516
      ],
      "state": "walkableArea"
    },
    {
      "frameInt": 16,
      "beforeTrans_pos": [
        1422,
        401
      ],
      "beforeTrans_chestDirection": [
        1471,
        351
      ],
      "pos": [
        1545,
        540
      ],
      "direction": [
        1611,
        457
      ],
      "state": "walkableArea"
    },
    {
      "frameInt": 17,
      "beforeTrans_pos": [
        1474,
        380
      ],
      "beforeTrans_chestDirection": [
        1523,
        330
      ],
      "pos": [
        1605,
        507
      ],
      "direction": [
        1678,
        419
      ],
      "state": "walkableArea"
    },
    {
      "frameInt": 18,
      "beforeTrans_pos": [
        1503,
        354
      ],
      "beforeTrans_chestDirection": [
        1521,
        286
      ],
      "pos": [
        1645,
        463
      ],
      "direction": [
        1699,
        325
      ],
      "state": "walkableArea"
    },
    {
      "frameInt": 19,
      "beforeTrans_pos": [
        1510,
        320
      ],
      "beforeTrans_chestDirection": [
        1528,
        252
      ],
      "pos": [
        1668,
        399
      ],
      "direction": [
        1729,
        240
      ],
      "state": "walkableArea"
    },
    {
      "frameInt": 20,
      "beforeTrans_pos": [
        1528,
        285
      ],
      "beforeTrans_chestDirection": [
        1528,
        215
      ],
      "pos": [
        1708,
        323
      ],
      "direction": [
        1756,
        130
      ],
      "state": "walkableArea"
    },
    {
      "frameInt": 21,
      "beforeTrans_pos": [
        1537,
        280
      ],
      "beforeTrans_chestDirection": [
        1518,
        212
      ],
      "pos": [
        1722,
        311
      ],
      "direction": [
        1744,
        120
      ],
      "state": "walkableArea"
    },
    {
      "frameInt": 22,
      "beforeTrans_pos": [
        1529,
        250
      ],
      "beforeTrans_chestDirection": [
        1494,
        189
      ],
      "pos": [
        1731,
        234
      ],
      "direction": [
        1726,
        37
      ],
      "state": "walkableArea"
    },
    {
      "frameInt": 23,
      "beforeTrans_pos": [
        1497,
        249
      ],
      "beforeTrans_chestDirection": [
        1462,
        188
      ],
      "pos": [
        1689,
        230
      ],
      "direction": [
        1676,
        29
      ],
      "state": "walkableArea"
    }
  ],
  "feature": {
    "ageIndex": 2,
    "genderType": 1,
    "humanType": "adult"
  }
}